<?xml version="1.0" encoding="UTF-8" ?>
<!DOCTYPE mapper PUBLIC "-//mybatis.org//DTD Mapper 3.0//EN" "http://mybatis.org/dtd/mybatis-3-mapper.dtd" >
<mapper namespace="com.example.demo.dao.gen.TImportRecordMapper" >
  <resultMap id="BaseResultMap" type="com.example.demo.entity.gen.TImportRecord" >
    <!--
      WARNING - @mbggenerated
      This element is automatically generated by MyBatis Generator, do not modify.
    -->
    <id column="id" property="id" jdbcType="BIGINT" />
    <result column="file_name" property="fileName" jdbcType="VARCHAR" />
    <result column="organ_code" property="organCode" jdbcType="VARCHAR" />
    <result column="type" property="type" jdbcType="VARCHAR" />
    <result column="import_time" property="importTime" jdbcType="TIMESTAMP" />
    <result column="import_status" property="importStatus" jdbcType="INTEGER" />
    <result column="error_msg" property="errorMsg" jdbcType="VARCHAR" />
  </resultMap>
  <sql id="Example_Where_Clause" >
    <!--
      WARNING - @mbggenerated
      This element is automatically generated by MyBatis Generator, do not modify.
    -->
    <where >
      <foreach collection="oredCriteria" item="criteria" separator="or" >
        <if test="criteria.valid" >
          <trim prefix="(" suffix=")" prefixOverrides="and" >
            <foreach collection="criteria.criteria" item="criterion" >
              <choose >
                <when test="criterion.noValue" >
                  and ${criterion.condition}
                </when>
                <when test="criterion.singleValue" >
                  and ${criterion.condition} #{criterion.value}
                </when>
                <when test="criterion.betweenValue" >
                  and ${criterion.condition} #{criterion.value} and #{criterion.secondValue}
                </when>
                <when test="criterion.listValue" >
                  and ${criterion.condition}
                  <foreach collection="criterion.value" item="listItem" open="(" close=")" separator="," >
                    #{listItem}
                  </foreach>
                </when>
              </choose>
            </foreach>
          </trim>
        </if>
      </foreach>
    </where>
  </sql>
  <sql id="Update_By_Example_Where_Clause" >
    <!--
      WARNING - @mbggenerated
      This element is automatically generated by MyBatis Generator, do not modify.
    -->
    <where >
      <foreach collection="example.oredCriteria" item="criteria" separator="or" >
        <if test="criteria.valid" >
          <trim prefix="(" suffix=")" prefixOverrides="and" >
            <foreach collection="criteria.criteria" item="criterion" >
              <choose >
                <when test="criterion.noValue" >
                  and ${criterion.condition}
                </when>
                <when test="criterion.singleValue" >
                  and ${criterion.condition} #{criterion.value}
                </when>
                <when test="criterion.betweenValue" >
                  and ${criterion.condition} #{criterion.value} and #{criterion.secondValue}
                </when>
                <when test="criterion.listValue" >
                  and ${criterion.condition}
                  <foreach collection="criterion.value" item="listItem" open="(" close=")" separator="," >
                    #{listItem}
                  </foreach>
                </when>
              </choose>
            </foreach>
          </trim>
        </if>
      </foreach>
    </where>
  </sql>
  <sql id="Base_Column_List" >
    <!--
      WARNING - @mbggenerated
      This element is automatically generated by MyBatis Generator, do not modify.
    -->
    id, file_name, organ_code, type, import_time, import_status, error_msg
  </sql>
  <select id="selectByExample" resultMap="BaseResultMap" parameterType="com.example.demo.entity.gen.TImportRecordExample" >
    <!--
      WARNING - @mbggenerated
      This element is automatically generated by MyBatis Generator, do not modify.
    -->
    select
    <if test="distinct" >
      distinct
    </if>
    <include refid="Base_Column_List" />
    from t_import_record
    <if test="_parameter != null" >
      <include refid="Example_Where_Clause" />
    </if>
    <if test="orderByClause != null" >
      order by ${orderByClause}
    </if>
  </select>
  <select id="selectByPrimaryKey" resultMap="BaseResultMap" parameterType="String" >
    <!--
      WARNING - @mbggenerated
      This element is automatically generated by MyBatis Generator, do not modify.
    -->
    select 
    <include refid="Base_Column_List" />
    from t_import_record
    where id = #{id,jdbcType=BIGINT}
  </select>
  <delete id="deleteByPrimaryKey" parameterType="String" >
    <!--
      WARNING - @mbggenerated
      This element is automatically generated by MyBatis Generator, do not modify.
    -->
    delete from t_import_record
    where id = #{id,jdbcType=BIGINT}
  </delete>
  <delete id="deleteByExample" parameterType="com.example.demo.entity.gen.TImportRecordExample" >
    <!--
      WARNING - @mbggenerated
      This element is automatically generated by MyBatis Generator, do not modify.
    -->
    delete from t_import_record
    <if test="_parameter != null" >
      <include refid="Example_Where_Clause" />
    </if>
  </delete>
  <insert id="insert" parameterType="com.example.demo.entity.gen.TImportRecord" >
    <!--
      WARNING - @mbggenerated
      This element is automatically generated by MyBatis Generator, do not modify.
    -->
    <selectKey resultType="String" keyProperty="id" order="BEFORE" >
      select uuid_short()
    </selectKey>
    insert into t_import_record (id, file_name, organ_code, 
      type, import_time, import_status, 
      error_msg)
    values (#{id,jdbcType=BIGINT}, #{fileName,jdbcType=VARCHAR}, #{organCode,jdbcType=VARCHAR}, 
      #{type,jdbcType=VARCHAR}, #{importTime,jdbcType=TIMESTAMP}, #{importStatus,jdbcType=INTEGER}, 
      #{errorMsg,jdbcType=VARCHAR})
  </insert>
  <insert id="insertSelective" parameterType="com.example.demo.entity.gen.TImportRecord" >
    <!--
      WARNING - @mbggenerated
      This element is automatically generated by MyBatis Generator, do not modify.
    -->
    <selectKey resultType="String" keyProperty="id" order="BEFORE" >
      select uuid_short()
    </selectKey>
    insert into t_import_record
    <trim prefix="(" suffix=")" suffixOverrides="," >
      id,
      <if test="fileName != null" >
        file_name,
      </if>
      <if test="organCode != null" >
        organ_code,
      </if>
      <if test="type != null" >
        type,
      </if>
      <if test="importTime != null" >
        import_time,
      </if>
      <if test="importStatus != null" >
        import_status,
      </if>
      <if test="errorMsg != null" >
        error_msg,
      </if>
    </trim>
    <trim prefix="values (" suffix=")" suffixOverrides="," >
      #{id,jdbcType=BIGINT},
      <if test="fileName != null" >
        #{fileName,jdbcType=VARCHAR},
      </if>
      <if test="organCode != null" >
        #{organCode,jdbcType=VARCHAR},
      </if>
      <if test="type != null" >
        #{type,jdbcType=VARCHAR},
      </if>
      <if test="importTime != null" >
        #{importTime,jdbcType=TIMESTAMP},
      </if>
      <if test="importStatus != null" >
        #{importStatus,jdbcType=INTEGER},
      </if>
      <if test="errorMsg != null" >
        #{errorMsg,jdbcType=VARCHAR},
      </if>
    </trim>
  </insert>
  <select id="countByExample" parameterType="com.example.demo.entity.gen.TImportRecordExample" resultType="java.lang.Integer" >
    <!--
      WARNING - @mbggenerated
      This element is automatically generated by MyBatis Generator, do not modify.
    -->
    select count(*) from t_import_record
    <if test="_parameter != null" >
      <include refid="Example_Where_Clause" />
    </if>
  </select>
  <update id="updateByExampleSelective" parameterType="map" >
    <!--
      WARNING - @mbggenerated
      This element is automatically generated by MyBatis Generator, do not modify.
    -->
    update t_import_record
    <set >
      <if test="record.id != null" >
        id = #{record.id,jdbcType=BIGINT},
      </if>
      <if test="record.fileName != null" >
        file_name = #{record.fileName,jdbcType=VARCHAR},
      </if>
      <if test="record.organCode != null" >
        organ_code = #{record.organCode,jdbcType=VARCHAR},
      </if>
      <if test="record.type != null" >
        type = #{record.type,jdbcType=VARCHAR},
      </if>
      <if test="record.importTime != null" >
        import_time = #{record.importTime,jdbcType=TIMESTAMP},
      </if>
      <if test="record.importStatus != null" >
        import_status = #{record.importStatus,jdbcType=INTEGER},
      </if>
      <if test="record.errorMsg != null" >
        error_msg = #{record.errorMsg,jdbcType=VARCHAR},
      </if>
    </set>
    <if test="_parameter != null" >
      <include refid="Update_By_Example_Where_Clause" />
    </if>
  </update>
  <update id="updateByExample" parameterType="map" >
    <!--
      WARNING - @mbggenerated
      This element is automatically generated by MyBatis Generator, do not modify.
    -->
    update t_import_record
    set id = #{record.id,jdbcType=BIGINT},
      file_name = #{record.fileName,jdbcType=VARCHAR},
      organ_code = #{record.organCode,jdbcType=VARCHAR},
      type = #{record.type,jdbcType=VARCHAR},
      import_time = #{record.importTime,jdbcType=TIMESTAMP},
      import_status = #{record.importStatus,jdbcType=INTEGER},
      error_msg = #{record.errorMsg,jdbcType=VARCHAR}
    <if test="_parameter != null" >
      <include refid="Update_By_Example_Where_Clause" />
    </if>
  </update>
  <update id="updateByPrimaryKeySelective" parameterType="com.example.demo.entity.gen.TImportRecord" >
    <!--
      WARNING - @mbggenerated
      This element is automatically generated by MyBatis Generator, do not modify.
    -->
    update t_import_record
    <set >
      <if test="fileName != null" >
        file_name = #{fileName,jdbcType=VARCHAR},
      </if>
      <if test="organCode != null" >
        organ_code = #{organCode,jdbcType=VARCHAR},
      </if>
      <if test="type != null" >
        type = #{type,jdbcType=VARCHAR},
      </if>
      <if test="importTime != null" >
        import_time = #{importTime,jdbcType=TIMESTAMP},
      </if>
      <if test="importStatus != null" >
        import_status = #{importStatus,jdbcType=INTEGER},
      </if>
      <if test="errorMsg != null" >
        error_msg = #{errorMsg,jdbcType=VARCHAR},
      </if>
    </set>
    where id = #{id,jdbcType=BIGINT}
  </update>
  <update id="updateByPrimaryKey" parameterType="com.example.demo.entity.gen.TImportRecord" >
    <!--
      WARNING - @mbggenerated
      This element is automatically generated by MyBatis Generator, do not modify.
    -->
    update t_import_record
    set file_name = #{fileName,jdbcType=VARCHAR},
      organ_code = #{organCode,jdbcType=VARCHAR},
      type = #{type,jdbcType=VARCHAR},
      import_time = #{importTime,jdbcType=TIMESTAMP},
      import_status = #{importStatus,jdbcType=INTEGER},
      error_msg = #{errorMsg,jdbcType=VARCHAR}
    where id = #{id,jdbcType=BIGINT}
  </update>
</mapper>